thingy52/__init__.py
thingy52/characteristics.py
thingy52/cli.py
thingy52/delegates.py
thingy52/services.py
thingy52/thingy52.py
thingy52/uuids.py
thingy52-0.1.5.dist-info/DESCRIPTION.rst
thingy52-0.1.5.dist-info/METADATA
thingy52-0.1.5.dist-info/RECORD
thingy52-0.1.5.dist-info/WHEEL
thingy52-0.1.5.dist-info/entry_points.txt
thingy52-0.1.5.dist-info/metadata.json
thingy52-0.1.5.dist-info/top_level.txt
