Metadata-Version: 2.0
Name: thingy52
Version: 0.1.5
Summary: Interface to Thingy:52
Home-page: https://github.com/SebastianRoll/thingy52
Author: Sebastian Roll
Author-email: sebastianroll84@gmail.com
License: MIT license
Keywords: thingy52
Platform: UNKNOWN
Classifier: Development Status :: 2 - Pre-Alpha
Classifier: Intended Audience :: Developers
Classifier: License :: OSI Approved :: MIT License
Classifier: Natural Language :: English
Classifier: Programming Language :: Python :: 2
Classifier: Programming Language :: Python :: 2.6
Classifier: Programming Language :: Python :: 2.7
Classifier: Programming Language :: Python :: 3
Classifier: Programming Language :: Python :: 3.3
Classifier: Programming Language :: Python :: 3.4
Classifier: Programming Language :: Python :: 3.5
Requires-Dist: Click (>=6.0)
Requires-Dist: bluepy (>=1.1.1)
